agentpm/__init__.py
agentpm/core.py
agentpm/py.typed
agentpm/types.py
agentpm/adapters/__init__.py
agentpm/adapters/langchain.py
agentpm-0.1.1.dist-info/METADATA
agentpm-0.1.1.dist-info/WHEEL
agentpm-0.1.1.dist-info/licenses/LICENSE
agentpm-0.1.1.dist-info/RECORD
