Metadata-Version: 2.4
Name: agentpm
Version: 0.1.1
Summary: AgentPM Python SDK
Project-URL: Homepage, https://github.com/agentpm-dev/sdk-python
Project-URL: Repository, https://github.com/agentpm-dev/sdk-python
Project-URL: Issues, https://github.com/agentpm-dev/sdk-python/issues
Project-URL: Changelog, https://github.com/agentpm-dev/sdk-python/releases
Author-email: AgentPM <dev@agentpm.dev>
License: MIT License
License-File: LICENSE
Keywords: agentpm,agents,ai,tools
Classifier: License :: OSI Approved :: MIT License
Classifier: Programming Language :: Python :: 3
Classifier: Programming Language :: Python :: 3 :: Only
Classifier: Programming Language :: Python :: 3.10
Classifier: Programming Language :: Python :: 3.11
Classifier: Programming Language :: Python :: 3.12
Classifier: Typing :: Typed
Requires-Python: >=3.10
Requires-Dist: semver>=3.0.0
Provides-Extra: dev
Requires-Dist: black>=24.8.0; extra == 'dev'
Requires-Dist: build>=1.2.1; extra == 'dev'
Requires-Dist: mypy>=1.11.0; extra == 'dev'
Requires-Dist: pre-commit>=3.8.0; extra == 'dev'
Requires-Dist: pytest-cov>=5.0.0; extra == 'dev'
Requires-Dist: pytest>=8.3.0; extra == 'dev'
Requires-Dist: ruff>=0.6.8; extra == 'dev'
Requires-Dist: twine>=5.1.1; extra == 'dev'
Provides-Extra: langchain
Requires-Dist: langchain-core>=0.2.0; extra == 'langchain'
